{
  "facture_BRO00001092.pdf": {
    "text": "Facture Brouillon\nN° : BRO00001092\nDate : 19/02/2025\nN° client : CLT00000004\nMonsieur Tabar Daniel\nNOMADS SURFING\n2590, Boulevard Paul Valery\nRésidence Le Véga Batiment A\nEmail : thomas@nomads-surfing.com\nSite web : https://www.nomads-surfing.com 34070 Montpellier\nFrance\nCatégorie de vente : 20.01.01\nCommentaire : planche avec répa donc remisée\nStatut paiement : A payer\nLibellé Qté PU HT Rem. Montant HT TVA\nART00000004 -PLA-BAL-LIN 1,00 766,67 € 0,00% 766,67 € 20,00%\nDétail de la TVA Total HT 766,67 €\nTVA 153,33 €\nCode Base HT Taux Montant\nTotal TTC 920,00 €\nNormale 766,67 € 20,00% 153,33 €\nRèglement Chèque\nEchéance(s) 920,00 € au 19/02/2025\nCoordonnées bancaires\nNom BPACA\nIBAN FR76 1090 7000 7486 0217 7452 573\nBIC CCBPFRPPBDX\nLe montant total s'élève à neuf cent vingt euros\nN° TVA : FR38832224539\nPas d'escompte pour règlement anticipé. En cas de retard de paiement, une pénalité égale à 3 fois le taux intérêt légal sera exigible (Article L 441-10, alinéa 12 du Code de Commerce).\nPour tout professionnel, en sus des indemnités de retard, toute somme, y compris l'acompte, non payée à sa date d'exigibilité produira de plein droit le paiement d'une indemnité\nforfaitaire de 40 euros due au titre des frais de recouvrement (Art. 441-6, I al. 12 du code de commerce et D. 441-5 ibidem).\nNOMADS SURFING - 22 RUE ANDRE MAGINOT 33700 MERIGNAC FRANCE - Siret : 83222453900011",
    "data": {
      "type_facture": "type facture non renseigné",
      "numero_facture": "",
      "date_facture": "19/02/2025",
      "numero_client": "CLT00000004",
      "nom_client": "Monsieur Tabar Daniel",
      "reglement": "cheque",
      "categorie_vente": "20.01.01",
      "commentaire": "planche avec répa donc remisée",
      "statut_paiement": "A payer",
      "TOTAL": {
        "total_ht": 766.67,
        "tva": 153.33,
        "total_ttc": 920.0,
        "acompte": 0.0
      },
      "detailTVA": [
        {
          "type": "TVAnormale",
          "base_ht": 766.67,
          "taux": 20.0,
          "montant": 153.33
        }
      ],
      "nombre_articles": 1,
      "articles": [
        {
          "reference": "ART00000004",
          "description": "PLA-BAL-LIN",
          "quantite": 1.0,
          "prix_unitaire": 766.67,
          "remise": 0.0,
          "montant_ht": 766.67,
          "tva": 20.0
        }
      ]
    }
  },
  "facture_FAC00000944.pdf": {
    "text": "Facture\nN° : FAC00000944\nDate : 11/02/2025\nN° client : CLT00000231\nMHCS\nNOMADS SURFING\n9 Avenue de Champagne\n51200 Epernay\nEmail : thomas@nomads-surfing.com\nSite web : https://www.nomads-surfing.com FRANCE\nCommande n°: 4501830197\n20.02\nLibellé Qté PU HT Rem. Montant HT TVA\nART00000283 -Planche de surf VEUVE CLICQUOT EGG 6'6 10,00 1 015,00 € 0,00% 10 150,00 € 20,00%\nART00000284 -Housse de planche VEUVE CLICQUOT 10,00 250,00 € 0,00% 2 500,00 € 20,00%\nART00000285 -Packaging FLEXI HEX - carton nid d'abeille 10,00 10,00 € 0,00% 100,00 € 20,00%\nDétail de la TVA Total HT 12 750,00 €\nAcompte(s) reçu(s) HT 6 375,00 €\nCode Base HT Taux Montant\nTotal HT net 6 375,00 €\nNormale 6 375,00 € 20,00% 1 275,00 €\nTVA 1 275,00 €\nRèglement Chèque\nTotal TTC 7 650,00 €\nEchéance(s) Acompte de 7 650,00 € au 16/12/2024\n7 650,00 € au 11/02/2025\nEchéance(s)\n7 650,00 € réglée le 16/12/2024 par Chèque\nréglée(s)\nCoordonnées bancaires\nNom BPACA\nIBAN FR76 1090 7000 7486 0217 7452 573\nBIC CCBPFRPPBDX\nLe montant total s'élève à sept mille six cent cinquante euros\nN° TVA : FR38832224539\nPas d'escompte pour règlement anticipé. En cas de retard de paiement, une pénalité égale à 3 fois le taux intérêt légal sera exigible (Article L 441-10, alinéa 12 du Code de Commerce).\nPour tout professionnel, en sus des indemnités de retard, toute somme, y compris l'acompte, non payée à sa date d'exigibilité produira de plein droit le paiement d'une indemnité\nforfaitaire de 40 euros due au titre des frais de recouvrement (Art. 441-6, I al. 12 du code de commerce et D. 441-5 ibidem).\nNOMADS SURFING - 22 RUE ANDRE MAGINOT 33700 MERIGNAC FRANCE - Siret : 83222453900011",
    "data": {
      "type_facture": "20.02",
      "numero_facture": "FAC00000944",
      "date_facture": "11/02/2025",
      "numero_client": "CLT00000231",
      "nom_client": "MHCS",
      "reglement": "cheque",
      "categorie_vente": "",
      "commentaire": "",
      "statut_paiement": "",
      "TOTAL": {
        "total_ht": 12750.0,
        "tva": 1275.0,
        "total_ttc": 7650.0,
        "acompte": 6375.0
      },
      "detailTVA": [],
      "nombre_articles": 3,
      "articles": [
        {
          "reference": "ART00000283",
          "description": "Planche de surf VEUVE CLICQUOT EGG 6'6",
          "quantite": 10.0,
          "prix_unitaire": 1015.0,
          "remise": 0.0,
          "montant_ht": 10150.0,
          "tva": 20.0
        },
        {
          "reference": "ART00000284",
          "description": "Housse de planche VEUVE CLICQUOT",
          "quantite": 10.0,
          "prix_unitaire": 250.0,
          "remise": 0.0,
          "montant_ht": 2500.0,
          "tva": 20.0
        },
        {
          "reference": "ART00000285",
          "description": "Packaging FLEXI HEX - carton nid d'abeille",
          "quantite": 10.0,
          "prix_unitaire": 10.0,
          "remise": 0.0,
          "montant_ht": 100.0,
          "tva": 20.0
        }
      ]
    }
  }
}